tetos-0.4.2.dist-info/METADATA
tetos-0.4.2.dist-info/WHEEL
tetos-0.4.2.dist-info/entry_points.txt
tetos-0.4.2.dist-info/licenses/LICENSE
tetos/__init__.py
tetos/__main__.py
tetos/azure.py
tetos/baidu.py
tetos/base.py
tetos/consts.py
tetos/edge.py
tetos/fish.py
tetos/google.py
tetos/minimax.py
tetos/openai.py
tetos/volc.py
tetos/xunfei.py
tetos-0.4.2.dist-info/RECORD
