Metadata-Version: 2.1
Name: tetos
Version: 0.4.2
Summary: Unified interface for multiple Text-to-Speech (TTS) providers
Keywords: tts,text-to-speech,speech,audio,ai,nlp
Author-Email: Frost Ming <me@frostming.com>
License: Apache-2.0
Classifier: Development Status :: 4 - Beta
Classifier: Intended Audience :: Developers
Classifier: License :: OSI Approved :: Apache Software License
Classifier: Programming Language :: Python :: 3
Classifier: Programming Language :: Python :: 3.8
Classifier: Programming Language :: Python :: 3.9
Classifier: Programming Language :: Python :: 3.10
Classifier: Programming Language :: Python :: 3.11
Classifier: Programming Language :: Python :: 3.12
Project-URL: Repository, https://github.com/frostming/tetos
Project-URL: Documentation, https://tetos.readthedocs.io/latest/
Requires-Python: >=3.8
Requires-Dist: edge-tts>=6.1.10
Requires-Dist: openai>=1.20.0
Requires-Dist: mutagen>=1.47.0
Requires-Dist: azure-cognitiveservices-speech>=1.37.0
Requires-Dist: anyio>=4.3.0
Requires-Dist: click>=8.1.7
Requires-Dist: google-cloud-texttospeech>=2.16.3
Requires-Dist: ormsgpack>=1.5.0
Requires-Dist: httpx-ws>=0.6.2
